aws_ip_check/__init__.py
aws_ip_check/check.py
aws_ip_check/cli.py
aws_ip_check-0.1.0.dist-info/METADATA
aws_ip_check-0.1.0.dist-info/WHEEL
aws_ip_check-0.1.0.dist-info/entry_points.txt
aws_ip_check-0.1.0.dist-info/top_level.txt
aws_ip_check-0.1.0.dist-info/RECORD
