Metadata-Version: 2.4
Name: aws-ip-check
Version: 0.1.0
Summary: Check if IPs belong to AWS ranges
Requires-Python: >=3.7
Requires-Dist: requests
Dynamic: requires-dist
Dynamic: requires-python
Dynamic: summary
